mnb/__init__.py
mnb/models.py
mnb-1.0.1.dist-info/METADATA
mnb-1.0.1.dist-info/WHEEL
mnb-1.0.1.dist-info/LICENSE
mnb-1.0.1.dist-info/RECORD
