Metadata-Version: 2.1
Name: mnb
Version: 1.0.1
Summary: Pythonic access to the exchange rate API hosted by Magyar Nemzeti Bank (MNB, Central Bank of Hungary)
Home-page: https://www.keresztury.com
License: MIT
Author: Balázs Keresztury
Author-email: balazs@keresztury.com
Requires-Python: >=3.8.1,<4.0.0
Classifier: Development Status :: 5 - Production/Stable
Classifier: License :: OSI Approved :: MIT License
Classifier: Programming Language :: Python :: 3
Classifier: Programming Language :: Python :: 3.9
Classifier: Programming Language :: Python :: 3.10
Classifier: Programming Language :: Python :: 3.11
Classifier: Topic :: Office/Business :: Financial
Requires-Dist: zeep (>=4.2.1,<5.0.0)
Project-URL: Repository, https://github.com/belidzs/mnb
